authy_package/__init__.py
authy_package/cache/__init__.py
authy_package/cache/abstract_cache.py
authy_package/cache/redis_cache.py
authy_package/cognito/__init__.py
authy_package/cognito/cognito_manager.py
authy_package/core/__init__.py
authy_package/core/auth_manager.py
authy_package/db/__init__.py
authy_package/db/abstract_db.py
authy_package/db/mongodb.py
authy_package/db/sql.py
authy_package/mfa/__init__.py
authy_package/mfa/mfa_setup.py
authy_package/social/__init__.py
authy_package/social/apple.py
authy_package/social/facebook.py
authy_package/social/github.py
authy_package/social/google.py
authy_package/utils/__init__.py
authy_package/utils/security.py
authy_package-0.1.9.dist-info/LICENSE
authy_package-0.1.9.dist-info/METADATA
authy_package-0.1.9.dist-info/WHEEL
authy_package-0.1.9.dist-info/RECORD
